Metadata-Version: 1.1
Name: pirouette
Version: 0.2.0
Summary: loading animation for cli apps
Home-page: https://github.com/walidsa3d/pirouette
Author: Walid Saad
Author-email: walid.sa3d@gmail.com
License: MIT
Platform: UNKNOWN
Classifier: Development Status :: 4 - Beta
Classifier: Environment :: Console
Classifier: Operating System :: POSIX
Classifier: Programming Language :: Python :: 2
Classifier: Topic :: Software Development :: Libraries :: Python Modules
